stable_hash_splitter/__init__.py
stable_hash_splitter/splitter.py
stable_hash_splitter/version.py
stable_hash_splitter-0.1.1.dist-info/licenses/LICENSE
stable_hash_splitter-0.1.1.dist-info/METADATA
stable_hash_splitter-0.1.1.dist-info/WHEEL
stable_hash_splitter-0.1.1.dist-info/top_level.txt
stable_hash_splitter-0.1.1.dist-info/RECORD
