Metadata-Version: 2.4
Name: stable-hash-splitter
Version: 0.1.1
Summary: A scikit-learn compatible splitter for deterministic, ID-based train/test splits that prevent data leakage.
Author-email: Baraa Hazzaa <baraa-hazaa00@hotmail.com>
License: MIT License
Project-URL: Homepage, https://github.com/BaraaHazzaa/stable-hash-splitter
Project-URL: Bug Tracker, https://github.com/BaraaHazzaa/stable-hash-splitter/issues
Keywords: machine-learning,scikit-learn,data-splitting,reproducible-research
Classifier: Development Status :: 3 - Alpha
Classifier: Intended Audience :: Science/Research
Classifier: License :: OSI Approved :: MIT License
Classifier: Programming Language :: Python :: 3
Classifier: Programming Language :: Python :: 3.7
Classifier: Programming Language :: Python :: 3.8
Classifier: Programming Language :: Python :: 3.9
Classifier: Programming Language :: Python :: 3.10
Classifier: Programming Language :: Python :: 3.11
Classifier: Topic :: Scientific/Engineering :: Artificial Intelligence
Requires-Python: >=3.7
License-File: LICENSE
Requires-Dist: numpy>=1.19.0
Requires-Dist: pandas>=1.3.0
Requires-Dist: scikit-learn>=1.0.0
Provides-Extra: dev
Requires-Dist: pytest; extra == "dev"
Requires-Dist: build; extra == "dev"
Requires-Dist: twine; extra == "dev"
Dynamic: license-file
